odoo/addons/sale_order_line_position/README.rst
odoo/addons/sale_order_line_position/__init__.py
odoo/addons/sale_order_line_position/__manifest__.py
odoo/addons/sale_order_line_position/i18n/sale_order_line_position.pot
odoo/addons/sale_order_line_position/models/__init__.py
odoo/addons/sale_order_line_position/models/sale_order.py
odoo/addons/sale_order_line_position/models/sale_order_line.py
odoo/addons/sale_order_line_position/readme/CONTRIBUTORS.rst
odoo/addons/sale_order_line_position/readme/DESCRIPTION.rst
odoo/addons/sale_order_line_position/readme/ROADMAP.rst
odoo/addons/sale_order_line_position/report/sale_order_report.xml
odoo/addons/sale_order_line_position/static/description/icon.png
odoo/addons/sale_order_line_position/static/description/index.html
odoo/addons/sale_order_line_position/tests/__init__.py
odoo/addons/sale_order_line_position/tests/test_sale_order_line_position.py
odoo/addons/sale_order_line_position/views/sale_order.xml
odoo13_addon_sale_order_line_position-13.0.1.0.1.dev4.dist-info/METADATA
odoo13_addon_sale_order_line_position-13.0.1.0.1.dev4.dist-info/WHEEL
odoo13_addon_sale_order_line_position-13.0.1.0.1.dev4.dist-info/top_level.txt
odoo13_addon_sale_order_line_position-13.0.1.0.1.dev4.dist-info/RECORD
